{
  "neoforge:conditions": [
    {
      "type": "neoforge:not",
      "value": {
        "type": "neoforge:tag_empty",
        "tag": "c:ingots/antimony"
      }
    },
    {
      "type": "neoforge:not",
      "value": {
        "type": "neoforge:tag_empty",
        "tag": "c:dusts/antimony"
      }
    }
  ],
  "type": "occultism:crushing",
  "ignore_crushing_multiplier": true,
  "ingredient": {
    "tag": "c:ingots/antimony"
  },
  "result": {
    "type": "occultism:tag",
    "count": 1,
    "tag": "c:dusts/antimony"
  }
}